simplevec/__init__.py
simplevec/models.py
simplevec-0.0.3.dist-info/LICENSE
simplevec-0.0.3.dist-info/METADATA
simplevec-0.0.3.dist-info/WHEEL
simplevec-0.0.3.dist-info/top_level.txt
simplevec-0.0.3.dist-info/RECORD
